vrt_lss_universal/__init__.py
vrt_lss_universal/api_client.py
vrt_lss_universal/api_response.py
vrt_lss_universal/configuration.py
vrt_lss_universal/exceptions.py
vrt_lss_universal/py.typed
vrt_lss_universal/rest.py
vrt_lss_universal/api/__init__.py
vrt_lss_universal/api/actualize_api.py
vrt_lss_universal/api/convert_api.py
vrt_lss_universal/api/plan_api.py
vrt_lss_universal/api/replan_api.py
vrt_lss_universal/api/system_api.py
vrt_lss_universal/models/__init__.py
vrt_lss_universal/models/actualize_settings.py
vrt_lss_universal/models/actualize_task.py
vrt_lss_universal/models/assigned_performer.py
vrt_lss_universal/models/assigned_transport.py
vrt_lss_universal/models/attribute.py
vrt_lss_universal/models/box.py
vrt_lss_universal/models/box_compatibilities.py
vrt_lss_universal/models/box_limits.py
vrt_lss_universal/models/break_rules.py
vrt_lss_universal/models/calculation_async_result.py
vrt_lss_universal/models/calculation_info.py
vrt_lss_universal/models/calculation_settings.py
vrt_lss_universal/models/calculation_state.py
vrt_lss_universal/models/calculation_status.py
vrt_lss_universal/models/capacity.py
vrt_lss_universal/models/capacity_cost.py
vrt_lss_universal/models/capacity_limit.py
vrt_lss_universal/models/capacity_multiplier.py
vrt_lss_universal/models/capacity_statistics_load.py
vrt_lss_universal/models/capacity_statistics_ratio.py
vrt_lss_universal/models/capacity_statistics_sum.py
vrt_lss_universal/models/cargo.py
vrt_lss_universal/models/cargo_action.py
vrt_lss_universal/models/cargo_action_type.py
vrt_lss_universal/models/cargo_compatibilities.py
vrt_lss_universal/models/cargo_rotation_type.py
vrt_lss_universal/models/check_result.py
vrt_lss_universal/models/compatibility_penalty.py
vrt_lss_universal/models/custom400_with_errors_and_warnings.py
vrt_lss_universal/models/demand.py
vrt_lss_universal/models/demand_extra_duration.py
vrt_lss_universal/models/demand_type.py
vrt_lss_universal/models/entity_error.py
vrt_lss_universal-7.29.3120.dist-info/METADATA
vrt_lss_universal-7.29.3120.dist-info/WHEEL
vrt_lss_universal-7.29.3120.dist-info/top_level.txt
vrt_lss_universal-7.29.3120.dist-info/RECORD
